custom_print/__init__.py
custom_print/cmdl.py
custom_print/fancy_cursor.py
custom_print/fancy_divider.py
custom_print/fancy_font_style.py
custom_print/fancy_format.py
custom_print/fancy_functions.py
custom_print/fancy_message.py
custom_print/fancy_pen.py
custom_print/pylo.py
custom_print/ref_names.py
custom_print-1.1.4.dist-info/METADATA
custom_print-1.1.4.dist-info/WHEEL
custom_print-1.1.4.dist-info/entry_points.txt
custom_print-1.1.4.dist-info/top_level.txt
custom_print-1.1.4.dist-info/RECORD
