Metadata-Version: 2.4
Name: custom_print
Version: 1.1.4
Summary: Customized Print Style
Home-page: https://github.com/acma82/Custom_Print
Author: Miguel Angel Aguilar Cuesta
Author-email: acma.mex@gmail.com
License: Everyone Can Use It At Their Own Risk
Keywords: print,custom print,fancy print,fancy message,font style,pretty print,divider
Classifier: Topic :: Utilities
Classifier: Programming Language :: Python :: 3.12
Classifier: Operating System :: Unix
Classifier: Operating System :: Microsoft :: Windows
Dynamic: author
Dynamic: author-email
Dynamic: classifier
Dynamic: description
Dynamic: description-content-type
Dynamic: home-page
Dynamic: keywords
Dynamic: license
Dynamic: summary
